practice_release_please_hamakou108-0.3.10.dist-info/METADATA
practice_release_please_hamakou108-0.3.10.dist-info/WHEEL
practice_release_please_hamakou108-0.3.10.dist-info/entry_points.txt
practice_release_please_hamakou108-0.3.10.dist-info/licenses/LICENSE
practice_release_please_hamakou108/__init__.py
practice_release_please_hamakou108/example.py
practice_release_please_hamakou108-0.3.10.dist-info/RECORD
