Metadata-Version: 2.1
Name: practice-release-please-hamakou108
Version: 0.3.10
Author-Email: hamakou108 <hamakou108@gmail.com>
License: MIT
Requires-Python: >=3.13
Requires-Dist: numpy>=1.24.2
